{
  "erc_kind": "erc20",
  "chainId": 8453,
  "address": "0x15c894b5b98218df17a6425056dc406badeb4365",
  "symbol": "aeroETH/AE",
  "decimals": 18,
  "name": "aeroETH/AEROUSD",
  "source": "https://api.curve.fi/api/getPools/base/factory-twocrypto",
  "token_kind": {
    "kind": "lp_share",
    "pool": {
      "protocol": {
        "name": "curve_twocrypto",
        "chain": "eip155:8453"
      },
      "pool_addr": "0x15c894b5b98218df17a6425056dc406badeb4365"
    },
    "underlyings": [
      {
        "key": {
          "standard": "erc20",
          "chain": "eip155:8453",
          "address": "0x56f131f372e30a6fbe11538f9a9949bae0f1eb07"
        }
      },
      {
        "key": {
          "standard": "erc20",
          "chain": "eip155:8453",
          "address": "0xc005b9833debcf5fe6cc5bc9ba4fd74bb382ae55"
        }
      }
    ],
    "share_form": "fungible",
    "shape": {
      "kind": "pooled"
    }
  }
}
