{
  "erc_kind": "erc20",
  "chainId": 8453,
  "address": "0x67f0c0918e13391d8b9bcc9a7faea1e519c02c22",
  "symbol": "L3/ETH",
  "decimals": 18,
  "name": "L3/WETH",
  "source": "https://api.curve.fi/api/getPools/base/factory-twocrypto",
  "token_kind": {
    "kind": "lp_share",
    "pool": {
      "protocol": {
        "name": "curve_twocrypto",
        "chain": "eip155:8453"
      },
      "pool_addr": "0x67f0c0918e13391d8b9bcc9a7faea1e519c02c22"
    },
    "underlyings": [
      {
        "key": {
          "standard": "erc20",
          "chain": "eip155:8453",
          "address": "0x46777c76dbbe40fabb2aab99e33ce20058e76c59"
        }
      },
      {
        "key": {
          "standard": "erc20",
          "chain": "eip155:8453",
          "address": "0x4200000000000000000000000000000000000006"
        }
      }
    ],
    "share_form": "fungible",
    "shape": {
      "kind": "pooled"
    }
  }
}
