{
  "erc_kind": "erc20",
  "chainId": 1,
  "address": "0x2673099769201c08e9a5e63b25fbaf25541a6557",
  "symbol": "eUSD3CRV3CRV-f",
  "decimals": 18,
  "name": "Curve.fi Factory USD Metapool: eUSD/3CRV",
  "source": "https://api.curve.fi/api/getPools/ethereum/factory",
  "token_kind": {
    "kind": "lp_share",
    "pool": {
      "protocol": {
        "name": "curve_stableswap",
        "chain": "eip155:1"
      },
      "pool_addr": "0x2673099769201c08e9a5e63b25fbaf25541a6557"
    },
    "underlyings": [
      {
        "key": {
          "standard": "erc20",
          "chain": "eip155:1",
          "address": "0xdf3ac4f479375802a821f7b7b46cd7eb5e4262cc"
        }
      },
      {
        "key": {
          "standard": "erc20",
          "chain": "eip155:1",
          "address": "0x6c3f90f043a72fa612cbac8115ee7e52bde6e490"
        }
      }
    ],
    "share_form": "fungible",
    "shape": {
      "kind": "pooled"
    }
  }
}
