{
  "erc_kind": "erc20",
  "chainId": 1,
  "address": "0x300ee2f505b449bed902bea8bc057593653fe9f0",
  "symbol": "xA-AZTEC",
  "decimals": 18,
  "name": "xAZTEC/AZTEC",
  "source": "https://api.curve.fi/api/getPools/ethereum/factory-stable-ng",
  "token_kind": {
    "kind": "lp_share",
    "pool": {
      "protocol": {
        "name": "curve_stableswap_ng",
        "chain": "eip155:1"
      },
      "pool_addr": "0x300ee2f505b449bed902bea8bc057593653fe9f0"
    },
    "underlyings": [
      {
        "key": {
          "standard": "erc20",
          "chain": "eip155:1",
          "address": "0xaaaaa01b76628f6d34ae030981b58660b3a1895e"
        }
      },
      {
        "key": {
          "standard": "erc20",
          "chain": "eip155:1",
          "address": "0xa27ec0006e59f245217ff08cd52a7e8b169e62d2"
        }
      }
    ],
    "share_form": "fungible",
    "shape": {
      "kind": "pooled"
    }
  }
}
