{
  "erc_kind": "erc20",
  "chainId": 1,
  "address": "0x4c1044a1b6474486a88cdd6a3d40f839abdae283",
  "symbol": "apyUSDapx",
  "decimals": 18,
  "name": "apyUSD-apxUSD",
  "source": "https://api.curve.fi/api/getPools/ethereum/factory-stable-ng",
  "token_kind": {
    "kind": "lp_share",
    "pool": {
      "protocol": {
        "name": "curve_stableswap_ng",
        "chain": "eip155:1"
      },
      "pool_addr": "0x4c1044a1b6474486a88cdd6a3d40f839abdae283"
    },
    "underlyings": [
      {
        "key": {
          "standard": "erc20",
          "chain": "eip155:1",
          "address": "0x38eeb52f0771140d10c4e9a9a72349a329fe8a6a"
        }
      },
      {
        "key": {
          "standard": "erc20",
          "chain": "eip155:1",
          "address": "0x98a878b1cd98131b271883b390f68d2c90674665"
        }
      }
    ],
    "share_form": "fungible",
    "shape": {
      "kind": "pooled"
    }
  }
}
