{
  "erc_kind": "erc20",
  "chainId": 1,
  "address": "0x59e256fbcfb261c805bb0d6145d3395823eaeffc",
  "symbol": "crDAIFRAX-f",
  "decimals": 18,
  "name": "Curve.fi Factory Crypto Pool: crDAI/FRAXBP",
  "source": "https://api.curve.fi/api/getPools/ethereum/factory-crypto",
  "token_kind": {
    "kind": "lp_share",
    "pool": {
      "protocol": {
        "name": "curve_cryptoswap",
        "chain": "eip155:1"
      },
      "pool_addr": "0xce756104d10e1fdc60c9c32a84b1bb19712e52ba"
    },
    "underlyings": [
      {
        "key": {
          "standard": "erc20",
          "chain": "eip155:1",
          "address": "0x9435f39c4a1a51765dd4294fc84fe024f5ace0d2"
        }
      },
      {
        "key": {
          "standard": "erc20",
          "chain": "eip155:1",
          "address": "0x3175df0976dfa876431c2e9ee6bc45b65d3473cc"
        }
      }
    ],
    "share_form": "fungible",
    "shape": {
      "kind": "pooled"
    }
  }
}
