{
  "erc_kind": "erc20",
  "chainId": 1,
  "address": "0x69b6da941e6a8960f480709281b87b1c32ff8366",
  "symbol": "crvsFRAX-f",
  "decimals": 18,
  "name": "Curve.fi Factory Plain Pool: crvUSD-sFRAX",
  "source": "https://api.curve.fi/api/getPools/ethereum/factory-crvusd",
  "token_kind": {
    "kind": "lp_share",
    "pool": {
      "protocol": {
        "name": "curve_stableswap",
        "chain": "eip155:1"
      },
      "pool_addr": "0x69b6da941e6a8960f480709281b87b1c32ff8366"
    },
    "underlyings": [
      {
        "key": {
          "standard": "erc20",
          "chain": "eip155:1",
          "address": "0xf939e0a03fb07f59a73314e73794be0e57ac1b4e"
        }
      },
      {
        "key": {
          "standard": "erc20",
          "chain": "eip155:1",
          "address": "0x03cb4438d015b9646d666316b617a694410c216d"
        }
      }
    ],
    "share_form": "fungible",
    "shape": {
      "kind": "pooled"
    }
  }
}
