{
  "erc_kind": "erc20",
  "chainId": 1,
  "address": "0x7be76a89fe1e95995164eeb8e0f18b4431474d3a",
  "symbol": "cvxPrisma-f",
  "decimals": 18,
  "name": "Curve.fi Factory Crypto Pool: cvxPrisma/PRISMA",
  "source": "https://api.curve.fi/api/getPools/ethereum/factory-crypto",
  "token_kind": {
    "kind": "lp_share",
    "pool": {
      "protocol": {
        "name": "curve_cryptoswap",
        "chain": "eip155:1"
      },
      "pool_addr": "0xc6ca529b988267602c86ae3d54ed3a3c9b48b909"
    },
    "underlyings": [
      {
        "key": {
          "standard": "erc20",
          "chain": "eip155:1",
          "address": "0x34635280737b5bfe6c7dc2fc3065d60d66e78185"
        }
      },
      {
        "key": {
          "standard": "erc20",
          "chain": "eip155:1",
          "address": "0xda47862a83dac0c112ba89c6abc2159b95afd71c"
        }
      }
    ],
    "share_form": "fungible",
    "shape": {
      "kind": "pooled"
    }
  }
}
