{
  "erc_kind": "erc20",
  "chainId": 1,
  "address": "0x8ea96fc70c577d59528c98c31bc4bf39027c1c3e",
  "symbol": "BBNSolvBTC",
  "decimals": 18,
  "name": "SolvBTC.BBN/SolvBTC",
  "source": "https://api.curve.fi/api/getPools/ethereum/factory-stable-ng",
  "token_kind": {
    "kind": "lp_share",
    "pool": {
      "protocol": {
        "name": "curve_stableswap_ng",
        "chain": "eip155:1"
      },
      "pool_addr": "0x8ea96fc70c577d59528c98c31bc4bf39027c1c3e"
    },
    "underlyings": [
      {
        "key": {
          "standard": "erc20",
          "chain": "eip155:1",
          "address": "0xd9d920aa40f578ab794426f5c90f6c731d159def"
        }
      },
      {
        "key": {
          "standard": "erc20",
          "chain": "eip155:1",
          "address": "0x7a56e1c57c7475ccf742a1832b028f0456652f97"
        }
      }
    ],
    "share_form": "fungible",
    "shape": {
      "kind": "pooled"
    }
  }
}
