{
  "erc_kind": "erc20",
  "chainId": 1,
  "address": "0xb2ebd0110126a2bb23252edf9add54385ce8bdb3",
  "symbol": "test-f",
  "decimals": 18,
  "name": "Curve.fi Factory Crypto Pool: test",
  "source": "https://api.curve.fi/api/getPools/ethereum/factory-crypto",
  "token_kind": {
    "kind": "lp_share",
    "pool": {
      "protocol": {
        "name": "curve_cryptoswap",
        "chain": "eip155:1"
      },
      "pool_addr": "0x9685aab3b578c55ce206a312095fc1fa73609e38"
    },
    "underlyings": [
      {
        "key": {
          "standard": "erc20",
          "chain": "eip155:1",
          "address": "0x95ad61b0a150d79219dcf64e1e6cc01f0b64c4ce"
        }
      },
      {
        "key": {
          "standard": "erc20",
          "chain": "eip155:1",
          "address": "0x3175df0976dfa876431c2e9ee6bc45b65d3473cc"
        }
      }
    ],
    "share_form": "fungible",
    "shape": {
      "kind": "pooled"
    }
  }
}
