{
  "erc_kind": "erc20",
  "chainId": 1,
  "address": "0xb38a31f12b9ad682c92441faeaa1fd8e33f4f6bd",
  "symbol": "uniETH-PT@30 Dec 2024",
  "decimals": 18,
  "name": "Napier uniETH-PT@30 Dec 2024",
  "source": "https://api.curve.fi/api/getPools/ethereum/factory-twocrypto",
  "token_kind": {
    "kind": "lp_share",
    "pool": {
      "protocol": {
        "name": "curve_twocrypto",
        "chain": "eip155:1"
      },
      "pool_addr": "0xb38a31f12b9ad682c92441faeaa1fd8e33f4f6bd"
    },
    "underlyings": [
      {
        "key": {
          "standard": "erc20",
          "chain": "eip155:1",
          "address": "0x1e5beb0240bb647f16fdf9e5c745df72eeb96e58"
        }
      },
      {
        "key": {
          "standard": "erc20",
          "chain": "eip155:1",
          "address": "0xf7e009b8111c09a906d1d84938745b9edeedfdde"
        }
      }
    ],
    "share_form": "fungible",
    "shape": {
      "kind": "pooled"
    }
  }
}
