{
  "erc_kind": "erc20",
  "chainId": 1,
  "address": "0xcec99cff3632cf1f16652cc5b1e80eb08be25983",
  "symbol": "pzETHstETH",
  "decimals": 18,
  "name": "pzETH/wstETH",
  "source": "https://api.curve.fi/api/getPools/ethereum/factory-stable-ng",
  "token_kind": {
    "kind": "lp_share",
    "pool": {
      "protocol": {
        "name": "curve_stableswap_ng",
        "chain": "eip155:1"
      },
      "pool_addr": "0xcec99cff3632cf1f16652cc5b1e80eb08be25983"
    },
    "underlyings": [
      {
        "key": {
          "standard": "erc20",
          "chain": "eip155:1",
          "address": "0x8c9532a60e0e7c6bbd2b2c1303f63ace1c3e9811"
        }
      },
      {
        "key": {
          "standard": "erc20",
          "chain": "eip155:1",
          "address": "0x7f39c581f595b53c5cb19bd0b3f8da6c935e2ca0"
        }
      }
    ],
    "share_form": "fungible",
    "shape": {
      "kind": "pooled"
    }
  }
}
