{
  "erc_kind": "erc20",
  "chainId": 1,
  "address": "0xef484de8c07b6e2d732a92b5f78e81b38f99f95e",
  "symbol": "crvDOLA",
  "decimals": 18,
  "name": "DOLA/FRAXPYUSD",
  "source": "https://api.curve.fi/api/getPools/ethereum/factory-stable-ng",
  "token_kind": {
    "kind": "lp_share",
    "pool": {
      "protocol": {
        "name": "curve_stableswap_ng",
        "chain": "eip155:1"
      },
      "pool_addr": "0xef484de8c07b6e2d732a92b5f78e81b38f99f95e"
    },
    "underlyings": [
      {
        "key": {
          "standard": "erc20",
          "chain": "eip155:1",
          "address": "0x865377367054516e17014ccded1e7d814edc9ce4"
        }
      },
      {
        "key": {
          "standard": "erc20",
          "chain": "eip155:1",
          "address": "0xa5588f7cdf560811710a2d82d3c9c99769db1dcb"
        }
      }
    ],
    "share_form": "fungible",
    "shape": {
      "kind": "pooled"
    }
  }
}
