{
  "erc_kind": "erc20",
  "chainId": 1,
  "address": "0xf1f435b05d255a5dbde37333c0f61da6f69c6127",
  "symbol": "cyb-tbtc",
  "decimals": 18,
  "name": "YB tBTC",
  "source": "https://etherscan.io/token/0xf1f435b05d255a5dbde37333c0f61da6f69c6127",
  "token_kind": {
    "kind": "lp_share",
    "pool": {
      "protocol": {
        "name": "curve_twocrypto",
        "chain": "eip155:1"
      },
      "pool_addr": "0xf1f435b05d255a5dbde37333c0f61da6f69c6127"
    },
    "underlyings": [
      {
        "key": {
          "standard": "erc20",
          "chain": "eip155:1",
          "address": "0xf939e0a03fb07f59a73314e73794be0e57ac1b4e"
        }
      },
      {
        "key": {
          "standard": "erc20",
          "chain": "eip155:1",
          "address": "0x18084fba666a33d37592fa2633fd49a74dd93a88"
        }
      }
    ],
    "share_form": "fungible",
    "shape": {
      "kind": "pooled"
    }
  }
}
