{
  "erc_kind": "erc20",
  "chainId": 1,
  "address": "0xf38a67da7a3a12aa12a9981ae6a79c0fdddd71ab",
  "symbol": "pxCVX-f",
  "decimals": 18,
  "name": "Curve.fi Factory Plain Pool: pxCVX/CVX",
  "source": "https://api.curve.fi/api/getPools/ethereum/factory",
  "token_kind": {
    "kind": "lp_share",
    "pool": {
      "protocol": {
        "name": "curve_stableswap",
        "chain": "eip155:1"
      },
      "pool_addr": "0xf38a67da7a3a12aa12a9981ae6a79c0fdddd71ab"
    },
    "underlyings": [
      {
        "key": {
          "standard": "erc20",
          "chain": "eip155:1",
          "address": "0xbce0cf87f513102f22232436cca2ca49e815c3ac"
        }
      },
      {
        "key": {
          "standard": "erc20",
          "chain": "eip155:1",
          "address": "0x4e3fbd56cd56c3e72c1403e103b45db9da5b9d2b"
        }
      }
    ],
    "share_form": "fungible",
    "shape": {
      "kind": "pooled"
    }
  }
}
