{
  "erc_kind": "erc20",
  "chainId": 1,
  "address": "0xfed2b54453f75634bcdaea5e5b11a3f99b9c28fa",
  "symbol": "USDC+LP-f",
  "decimals": 18,
  "name": "Curve.fi Factory Crypto Pool: USDC+",
  "source": "https://api.curve.fi/api/getPools/ethereum/factory-crypto",
  "token_kind": {
    "kind": "lp_share",
    "pool": {
      "protocol": {
        "name": "curve_cryptoswap",
        "chain": "eip155:1"
      },
      "pool_addr": "0xf2b25362a03f6eacca8de8d5350a9f37944c1e59"
    },
    "underlyings": [
      {
        "key": {
          "standard": "erc20",
          "chain": "eip155:1",
          "address": "0xa0b86991c6218b36c1d19d4a2e9eb0ce3606eb48"
        }
      },
      {
        "key": {
          "standard": "erc20",
          "chain": "eip155:1",
          "address": "0xfc0b1eef20e4c68b3dcf36c4537cfa7ce46ca70b"
        }
      }
    ],
    "share_form": "fungible",
    "shape": {
      "kind": "pooled"
    }
  }
}
